thonny_python_api_docs-0.0.2.dist-info/licenses/LICENSE-MIT
thonny_python_api_docs-0.0.2.dist-info/licenses/LICENSE-PSFL
thonnycontrib/thonny-python-api-docs/__init__.py
thonnycontrib/thonny-python-api-docs/python-documentation/.buildinfo
thonnycontrib/thonny-python-api-docs/python-documentation/about.html
thonnycontrib/thonny-python-api-docs/python-documentation/bugs.html
thonnycontrib/thonny-python-api-docs/python-documentation/contents.html
thonnycontrib/thonny-python-api-docs/python-documentation/copyright.html
thonnycontrib/thonny-python-api-docs/python-documentation/download.html
thonnycontrib/thonny-python-api-docs/python-documentation/genindex-A.html
thonnycontrib/thonny-python-api-docs/python-documentation/genindex-B.html
thonnycontrib/thonny-python-api-docs/python-documentation/genindex-C.html
thonnycontrib/thonny-python-api-docs/python-documentation/genindex-D.html
thonnycontrib/thonny-python-api-docs/python-documentation/genindex-E.html
thonnycontrib/thonny-python-api-docs/python-documentation/genindex-F.html
thonnycontrib/thonny-python-api-docs/python-documentation/genindex-G.html
thonnycontrib/thonny-python-api-docs/python-documentation/genindex-H.html
thonnycontrib/thonny-python-api-docs/python-documentation/genindex-I.html
thonnycontrib/thonny-python-api-docs/python-documentation/genindex-J.html
thonnycontrib/thonny-python-api-docs/python-documentation/genindex-K.html
thonnycontrib/thonny-python-api-docs/python-documentation/genindex-L.html
thonnycontrib/thonny-python-api-docs/python-documentation/genindex-M.html
thonnycontrib/thonny-python-api-docs/python-documentation/genindex-N.html
thonnycontrib/thonny-python-api-docs/python-documentation/genindex-O.html
thonnycontrib/thonny-python-api-docs/python-documentation/genindex-P.html
thonnycontrib/thonny-python-api-docs/python-documentation/genindex-Q.html
thonnycontrib/thonny-python-api-docs/python-documentation/genindex-R.html
thonnycontrib/thonny-python-api-docs/python-documentation/genindex-S.html
thonnycontrib/thonny-python-api-docs/python-documentation/genindex-Symbols.html
thonny_python_api_docs-0.0.2.dist-info/METADATA
thonny_python_api_docs-0.0.2.dist-info/WHEEL
thonny_python_api_docs-0.0.2.dist-info/top_level.txt
thonny_python_api_docs-0.0.2.dist-info/RECORD
